audresample/__init__.py
audresample/core/__init__.py
audresample/core/api.py
audresample/core/config.py
audresample/core/define.py
audresample/core/lib.py
audresample/core/bin/manylinux_2_17_armv7l/libaudresample.so
audresample/define/__init__.py
audresample-1.3.2.dist-info/LICENSE
audresample-1.3.2.dist-info/METADATA
audresample-1.3.2.dist-info/WHEEL
audresample-1.3.2.dist-info/top_level.txt
audresample-1.3.2.dist-info/RECORD
