Metadata-Version: 2.1
Name: audresample
Version: 1.3.2
Summary: Provides functions to resample and remix a signal
Home-page: https://github.com/audeering/audresample/
Author: Johannes Wagner, Andrea Crespi, Hagen Wierstorf
Author-email: jwagner@audeering.com, acrespi@audeering.com, hwierstorf@audeering.com
License: MIT
Project-URL: Documentation, https://audeering.github.io/audresample/
Keywords: audio,dsp,resample,remix
Platform: any
Classifier: Development Status :: 5 - Production/Stable
Classifier: Intended Audience :: Science/Research
Classifier: Intended Audience :: Developers
Classifier: License :: OSI Approved :: MIT License
Classifier: Operating System :: OS Independent
Classifier: Programming Language :: Python
Classifier: Programming Language :: Python :: 3
Classifier: Programming Language :: Python :: 3.7
Classifier: Programming Language :: Python :: 3.8
Classifier: Programming Language :: Python :: 3.9
Classifier: Programming Language :: Python :: 3.10
Classifier: Programming Language :: Python :: 3.11
Classifier: Topic :: Scientific/Engineering
License-File: LICENSE
Requires-Dist: numpy
